drb/addons/metadata/sentinel3/__init__.py
drb/addons/metadata/sentinel3/_version.py
drb/addons/metadata/sentinel3/cortex.yaml
drb_metadata_sentinel3-1.3.0.dist-info/LICENCE.txt
drb_metadata_sentinel3-1.3.0.dist-info/METADATA
drb_metadata_sentinel3-1.3.0.dist-info/WHEEL
drb_metadata_sentinel3-1.3.0.dist-info/entry_points.txt
drb_metadata_sentinel3-1.3.0.dist-info/top_level.txt
drb_metadata_sentinel3-1.3.0.dist-info/RECORD
