Metadata-Version: 2.1
Name: drb-metadata-sentinel3
Version: 1.3.0
Summary: Sentinel-3 Product Metadata
Author: GAEL Systems
Author-email: drb-python@gael.fr
License: LGPLv3
Project-URL: Source, https://gitlab.com/drb-python/add-ons/metadata/add-ons/sentinel-3
Classifier: Programming Language :: Python :: 3.8
Classifier: License :: OSI Approved :: GNU Lesser General Public License v3 (LGPLv3)
Requires-Python: >=3.8
License-File: LICENCE.txt
Requires-Dist: drb-topic-sentinel3 ~=1.2.0
Requires-Dist: drb-metadata ~=1.3.0
